{
	"name": "Plotka Dark",
	"author": "Vitória Lopes",
	"type": "dark",
	"maintainers": [
		"Vitoria Lopes <vilopesp@hotmail.com>"
	],

	"colors": {
		"settings.textInputBackground": "#292929",
		"settings.numberInputBackground": "#292929",

		"menu.background": "#252526",
		"menu.foreground": "#CCCCCC",

		"statusBarItem.remoteForeground": "#FFF",
		"statusBarItem.remoteBackground": "#16825D",

		"contrastBorder": "#252525",
		"focusBorder": "#303030",
		"foreground": "#cbcdd2",
		"errorForeground": "#eb3d54",

		"button.background": "#2F3137",
		"button.foreground": "#cbcdd2",
		"button.hoverBackground": "#505050",
		"dropdown.background": "#252525",
		"dropdown.border": "#303030",
		"dropdown.foreground": "#cbcdd2",

		"input.border": "#686b78",
		"input.foreground": "#cbcdd2",
		"input.placeholderForeground": "#cbcdd2",
		"inputOption.activeBorder": "#303030",
		"inputValidation.errorBackground": "#eb3d54",
		"inputValidation.errorBorder": "#eb3d54",
		"inputValidation.infoBackground": "#4fb4d8",
		"inputValidation.infoBorder": "#4fb4d8",
		"inputValidation.warningBackground": "#ef7c2a",
		"inputValidation.warningBorder": "#ef7c2a",

		"scrollbarSlider.activeBackground": "#303030",
		"scrollbarSlider.background": "#30303080",
		"scrollbarSlider.hoverBackground": "#0FBBFF",

		"badge.background": "#252525",
		"badge.foreground": "#cbcdd2",
		"progressBar.background": "#4fb4d8",

		"list.activeSelectionBackground": "#303030",
		"list.activeSelectionForeground": "#d0d0d0",

		"list.errorForeground": "#ef7c2a",
		"list.warningForeground": "#2292A4",
		"list.focusBackground": "#494A4E",
		"list.focusForeground": "#cbcdd2",
		"list.highlightForeground": "#cbcdd2",
		"list.hoverBackground": "#494a4e",
		"list.hoverForeground": "#B2B4B8",
		"list.inactiveSelectionBackground": "#303030",
		"list.inactiveSelectionForeground": "#d0d0d0",

		"activityBar.background": "#252525",
		"activityBar.foreground": "#0FBBFF",
		"activityBar.border": "#303030",
		"activityBarBadge.background": "#4fb4d8",
		"activityBarBadge.foreground": "#d0d0d0",

		"sideBar.background": "#252525",
		"sideBar.foreground": "#cbcdd2",
		"sideBar.border": "#252525",
		"sideBarTitle.foreground": "#cbcdd2",
		"sideBarSectionHeader.background": "#303030",
		"sideBarSectionHeader.foreground": "#cbcdd2",

		"editorGroupHeader.tabsBackground": "#252525",
		"editorGroupHeader.tabsBorder": "#252525",

		"tab.activeBackground": "#252525",
		"tab.activeForeground": "#cbcdd2",
		"tab.border": "#303030",
		"tab.activeBorder": "#0FBBFF",
		"tab.unfocusedActiveBorder": "#0FBBFF",
		"tab.inactiveBackground": "#303030",
		"tab.inactiveForeground": "#7d7d7d",
		"tab.unfocusedInactiveForeground": "#202020",

		"editor.background": "#252525",
		"editor.foreground": "#cbcdd2",
		"editorLineNumber.foreground": "#686b78",
		"editorCursor.foreground": "#4fb4d8",
		"editor.selectionBackground": "#7a717180",

		"editor.selectionHighlightBackground": "#1f365190",
		"editor.inactiveSelectionBackground": "#7a717170",
		"editor.wordHighlightBackground": "#2F3137",
		"editor.wordHighlightStrongBackground": "#2F3137",
		"editor.findMatchHighlightBackground": "#2F3137",
		"editor.findRangeHighlightBackground": "#2F3137",
		"editor.hoverHighlightBackground": "#2F3137",
		"editor.lineHighlightBackground": "#023b6930",
		"editor.lineHighlightBorder": "#023b6930",
		"editorLink.activeForeground": "#6dd2f6",

		"editor.rangeHighlightBackground": "#2F3137",
		"editorIndentGuide.activeBackground": "#686b78",
		"editorIndentGuide.background": "#303030",
		"editorRuler.foreground": "#686b78",

		"editorOverviewRuler.currentContentForeground": "#4fb4d8",
		"editorOverviewRuler.incomingContentForeground": "#4fb4d8",
		"editorOverviewRuler.commonContentForeground": "#4fb4d8",
		"editorOverviewRuler.addedForeground": "#2292A4",
		"editorOverviewRuler.deletedForeground": "#eb3d54",
		"editorOverviewRuler.errorForeground": "#eb3d54",
		"editorOverviewRuler.modifiedForeground": "#e5cd52",
		"editorOverviewRuler.warningForeground": "#ef7c2a",

		"editorError.foreground": "#eb3d54",
		"editorWarning.foreground": "#2292A4",
		"editorGutter.modifiedBackground": "#e5cd52",
		"editorGutter.addedBackground": "#2292A4",
		"editorGutter.deletedBackground": "#eb3d54",

		"diffEditor.insertedTextBackground": "#2292A425",
		"diffEditor.insertedTextBorder": "#2292A425",
		"diffEditor.removedTextBackground": "#eb3d5425",
		"diffEditor.removedTextBorder": "#eb3d5425",

		"editorWidget.background": "#252525",
		"editorHoverWidget.background": "#252525",
		"editorHoverWidget.border": "#4fb4d8",

		"debugExceptionWidget.background": "#252525",
		"debugExceptionWidget.border": "#4fb4d8",

		"editorMarkerNavigation.background": "#252525",
		"editorMarkerNavigationError.background": "#eb3d54",
		"editorMarkerNavigationWarning.background": "#ef7c2a",

		"peekView.border": "#4fb4d8",
		"peekViewEditor.matchHighlightBackground": "#2F3137",
		"peekViewResult.fileForeground": "#cbcdd2",
		"peekViewResult.lineForeground": "#cbcdd2",
		"peekViewResult.matchHighlightBackground": "#2F3137",
		"peekViewResult.selectionForeground": "#cbcdd2",
		"peekViewTitle.background": "#252525",
		"peekViewTitleLabel.foreground": "#cbcdd2",

		"merge.currentHeaderBackground": "#4fb4d8",
		"merge.incomingHeaderBackground": "#4fb4d8",

		"panel.background": "#252525",
		"panel.border": "#303030",
		"panelTitle.activeBorder": "#4fb4d8",
		"panelTitle.activeForeground": "#cbcdd2",

		"statusBar.background": "#252525",
		"statusBar.foreground": "#686b78",
		"statusBar.border": "#252525",
		"statusBar.noFolderBackground": "#252525",

		"extensionButton.prominentForeground": "#252525",
		"extensionButton.prominentBackground": "#535458",
		"extensionButton.prominentHoverBackground": "#535458",
		"pickerGroup.foreground": "#4fb4d8",

		"terminal.ansiWhite": "#cbcdd2",
		"terminal.ansiBlack": "#818491",
		"terminal.ansiBlue": "#4fb4d8",
		"terminal.ansiCyan": "#4fb4d8",
		"terminal.ansiGreen": "#2292A4",
		"terminal.ansiMagenta": "#eb3d54",
		"terminal.ansiRed": "#eb3d54",
		"terminal.ansiYellow": "#e5cd52",
		"terminal.ansiBrightWhite": "#cbcdd2",
		"terminal.ansiBrightBlack": "#818491",
		"terminal.ansiBrightBlue": "#4fb4d8",
		"terminal.ansiBrightCyan": "#4fb4d8",
		"terminal.ansiBrightGreen": "#2292A4",
		"terminal.ansiBrightMagenta": "#2292A4",
		"terminal.ansiBrightRed": "#eb3d54",
		"terminal.ansiBrightYellow": "#e5cd52",

		"debugToolBar.background": "#252525",

		"textLink.foreground": "#4fb4d8",
		"textLink.activeForeground": "#6dd2f6",

		"gitDecoration.modifiedResourceForeground": "#e5cd52",
		"gitDecoration.deletedResourceForeground": "#eb3d54",
		"gitDecoration.untrackedResourceForeground": "#2292A4",

		"textPreformat.foreground": "#e5cd52"
	},

	"tokenColors": [
		{
			"name": "Function declarations",
			"scope": [
				"entity.name.function",
				"support.function",
				"support.constant.handlebars",
				"source.powershell variable.other.member",
				"entity.name.operator.custom-literal"
			],
			"settings": {
				"foreground": "#DCDCAA"
			}
		},
		{
			"name": "Types declaration and references",
			"scope": [
				"meta.return-type",
				"support.class",
				"support.type",
				"entity.name.type",
				"entity.name.namespace",
				"entity.other.attribute",
				"entity.name.scope-resolution",
				"entity.name.class",
				"storage.type.numeric.go",
				"storage.type.byte.go",
				"storage.type.boolean.go",
				"storage.type.string.go",
				"storage.type.uintptr.go",
				"storage.type.error.go",
				"storage.type.rune.go",
				"storage.type.cs",
				"storage.type.generic.cs",
				"storage.type.modifier.cs",
				"storage.type.variable.cs",
				"storage.type.annotation.java",
				"storage.type.generic.java",
				"storage.type.java",
				"storage.type.object.array.java",
				"storage.type.primitive.array.java",
				"storage.type.primitive.java",
				"storage.type.token.java",
				"storage.type.groovy",
				"storage.type.annotation.groovy",
				"storage.type.parameters.groovy",
				"storage.type.generic.groovy",
				"storage.type.object.array.groovy",
				"storage.type.primitive.array.groovy",
				"storage.type.primitive.groovy"
			],
			"settings": {
				"foreground": "#4EC9B0"
			}
		},
		{
			"name": "Types declaration and references, TS grammar specific",
			"scope": [
				"meta.type.cast.expr",
				"meta.type.new.expr",
				"support.constant.math",
				"support.constant.dom",
				"support.constant.json",
				"entity.other.inherited-class"
			],
			"settings": {
				"foreground": "#4EC9B0"
			}
		},
		{
			"name": "Control flow / Special keywords",
			"scope": [
				"keyword.control",
				"source.cpp keyword.operator.new",
				"keyword.operator.delete",
				"keyword.other.using",
				"keyword.other.operator",
				"entity.name.operator"
			],
			"settings": {
				"foreground": "#C586C0"
			}
		},
		{
			"name": "Variable and parameter name",
			"scope": [
				"variable",
				"meta.definition.variable.name",
				"support.variable",
				"entity.name.variable"
			],
			"settings": {
				"foreground": "#9CDCFE"
			}
		},
		{
			"name": "Constants and enums",
			"scope": [
				"variable.other.constant",
				"variable.other.enummember"
			],
			"settings": {
				"foreground": "#4FC1FF"
			}
		},
		{
			"name": "Object keys, TS grammar specific",
			"scope": [
				"meta.object-literal.key"
			],
			"settings": {
				"foreground": "#9CDCFE"
			}
		},
		{
			"name": "CSS property value",
			"scope": [
				"support.constant.property-value",
				"support.constant.font-name",
				"support.constant.media-type",
				"support.constant.media",
				"constant.other.color.rgb-value",
				"constant.other.rgb-value",
				"support.constant.color"
			],
			"settings": {
				"foreground": "#CE9178"
			}
		},
		{
			"name": "Regular expression groups",
			"scope": [
				"punctuation.definition.group.regexp",
				"punctuation.definition.group.assertion.regexp",
				"punctuation.definition.character-class.regexp",
				"punctuation.character.set.begin.regexp",
				"punctuation.character.set.end.regexp",
				"keyword.operator.negation.regexp",
				"support.other.parenthesis.regexp"
			],
			"settings": {
				"foreground": "#CE9178"
			}
		},
		{
			"scope": [
				"constant.character.character-class.regexp",
				"constant.other.character-class.set.regexp",
				"constant.other.character-class.regexp",
				"constant.character.set.regexp"
			],
			"settings": {
				"foreground": "#d16969"
			}
		},
		{
			"scope": [
				"keyword.operator.or.regexp",
				"keyword.control.anchor.regexp"
			],
			"settings": {
				"foreground": "#DCDCAA"
			}
		},
		{
			"scope": "keyword.operator.quantifier.regexp",
			"settings": {
				"foreground": "#d7ba7d"
			}
		},
		{
			"scope": "constant.character",
			"settings": {
				"foreground": "#569cd6"
			}
		},
		{
			"scope": "constant.character.escape",
			"settings": {
				"foreground": "#d7ba7d"
			}
		},
		{
			"scope": "entity.name.label",
			"settings": {
				"foreground": "#C8C8C8"
			}
		},
		{
			"name": "Punctuation",
			"scope": [
				"meta",
				"meta.brace.round.js",
				"meta.function-call"
			],
			"settings": {
				"foreground": "#EEB150"
			}
		},
		{
			"name": "meta-value",
			"scope": ["meta.property-value.css"],
			"settings": {
				"foreground": "#C0C0C0"
			}
		},
		{
			"name": "Function declarations",
			"scope": [
				"entity.name.function",

				"support.constant.handlebars"
			],
			"settings": {
				"foreground": "#01D6A7",
				"fontStyle": "italic"
			}
		},
		{
			"name": "Function declarations",
			"scope": [
				"support.function"
			],
			"settings": {
				"foreground": "#01D6A7",
				"fontStyle": "italic"
			}
		},

		{
			"name": "Types declaration and references",
			"scope": [
				"meta.return-type",
				"support.class",
				"support.type",
				"entity.name.type",
				"entity.name.class",
				"storage.type.numeric.go",
				"storage.type.byte.go",
				"storage.type.boolean.go",
				"storage.type.string.go",
				"storage.type.uintptr.go",
				"storage.type.cs",
				"storage.type.generic.cs",
				"storage.type.modifier.cs",
				"storage.type.variable.cs",
				"storage.type.annotation.java",
				"storage.type.generic.java",
				"storage.type.java",
				"storage.type.object.array.java",
				"storage.type.primitive.array.java",
				"storage.type.primitive.java",
				"storage.type.token.java",
				"storage.type.groovy",
				"storage.type.annotation.groovy",
				"storage.type.parameters.groovy",
				"storage.type.generic.groovy",
				"storage.type.object.array.groovy",
				"storage.type.primitive.array.groovy",
				"storage.type.primitive.groovy"
			],
			"settings": {
				"foreground": "#E2E3E4"
			}
		},
		{
			"name": "Types declaration and references, TS grammar specific",
			"scope": [
				"meta.type.cast.expr",
				"meta.type.new.expr",
				"support.constant.math",
				"support.constant.dom",
				"support.constant.json",
				"entity.other.inherited-class"
			],
			"settings": {
				"foreground": "#FDE091"
			}
		},
		{
			"name": "Control flow keywords",
			"scope": "keyword.control",
			"settings": {
				"foreground": "#04C0E0",
				"fontStyle": "italic"
			}
		},
		{
			"name": "Variable and parameter name",
			"scope": [
				"variable",
				"meta.definition.variable.name",
				"support.variable"
			],
			"settings": {
				"foreground": "#e2e3e4"
			}
		},
		{
			"name": "Variable objetc",
			"scope": [
				"variable.other.object.property"
			],
			"settings": {
				"foreground": "#eeb150"
			}
		},
		{
			"name": "Variable objetc",
			"scope": [
				"variable.other.readwrite"
			],
			"settings": {
				"foreground": "#B98EFF"
			}
		},

		{
			"name": "Variable sla",
			"scope": [
				"variable.other.property",
				"variable.other.constant"
			],
			"settings": {
				"foreground": "#B98EFF"
			}
		},
		{
			"name": "Object keys, TS grammar specific",
			"scope": ["meta.object-literal.key"],
			"settings": {
				"foreground": "#01D6A7"
			}
		},
		{
			"name": "CSS property value and quotes",
			"scope": [
				"support.constant.property-value",
				"support.constant.font-name",
				"support.constant.media-type",
				"support.constant.media",
				"constant.other.color.rgb-value",
				"constant.other.rgb-value",
				"support.constant.color"
			],
			"settings": {
				"foreground": "#EEB772"
			}
		},
		{
			"name": "Regular expression groups",
			"scope": [
				"punctuation.definition.group.regexp",
				"punctuation.definition.group.assertion.regexp",
				"punctuation.definition.character-class.regexp",
				"punctuation.character.set.begin.regexp",
				"punctuation.character.set.end.regexp",
				"keyword.operator.negation.regexp",
				"support.other.parenthesis.regexp"
			],
			"settings": {
				"foreground": "#eeb150"
			}
		},
		{
			"scope": [
				"constant.character.character-class.regexp",
				"constant.other.character-class.set.regexp",
				"constant.other.character-class.regexp",
				"constant.character.set.regexp"
			],
			"settings": {
				"foreground": "#d16969"
			}
		},
		{
			"scope": ["keyword.operator.or.regexp", "keyword.control.anchor.regexp"],
			"settings": {
				"foreground": "#DCDCAA"
			}
		},
		{
			"scope": "keyword.operator.quantifier.regexp",
			"settings": {
				"foreground": "#d7ba7d"
			}
		},
		{
			"scope": "constant.character",
			"settings": {
				"foreground": "#FDE091"
			}
		},
		{
			"scope": "constant.character.escape",
			"settings": {
				"foreground": "#d7ba7d"
			}
		},
		{
			"scope": ["meta.embedded", "source.groovy.embedded"],
			"settings": {
				"foreground": "#e2e3e4"
			}
		},
		{
			"scope": "emphasis",
			"settings": {
				"fontStyle": "italic"
			}
		},
		{
			"scope": "strong",
			"settings": {
				"fontStyle": "bold"
			}
		},
		{
			"scope": "header",
			"settings": {
				"foreground": "#000080"
			}
		},
		{
			"scope": ["comment", "punctuation.definition.comment"],
			"settings": {
				"foreground": "#636363",
				"fontStyle": "italic"
			}
		},
		{
			"scope": "constant.language",
			"settings": {
				"foreground": "#FDE091",
				"fontStyle": "italic"
			}
		},
		{
			"scope": ["constant.numeric"],
			"settings": {
				"foreground": "#E2E3E4"
			}
		},
		{
			"scope": "constant.regexp",
			"settings": {
				"foreground": "#646695"
			}
		},

		{
			"scope": "entity.name.tag.css",
			"settings": {
				"foreground": "#B98EFF"
			}
		},
		{
			"scope": [
				"entity.other.attribute-name.class.css",
				"entity.other.attribute-name.class.mixin.css",
				"entity.other.attribute-name.id.css",
				"source.css.less entity.other.attribute-name.id",
				"entity.other.attribute-name.attribute.scss",
				"entity.other.attribute-name.scss"
			],
			"settings": {
				"foreground": "#B98EFF"
			}
		},
		{
			"name": "Pseudo-Elements CSS",
			"scope": [
				"entity.other.attribute-name.pseudo-class.css",
				"entity.other.attribute-name.parent-selector.css",
				"entity.other.attribute-name.pseudo-element.css"
			],
			"settings": {
				"foreground": "#01D6A7",
				"fontStyle": "italic"
			}
		},
		{
			"scope": "invalid",
			"settings": {
				"foreground": "#f44747"
			}
		},
		{
			"scope": "markup.underline",
			"settings": {
				"fontStyle": "underline"
			}
		},
		{
			"scope": "markup.bold",
			"settings": {
				"fontStyle": "bold",
				"foreground": "#FDE091"
			}
		},
		{
			"scope": "markup.heading",
			"settings": {
				"fontStyle": "bold",
				"foreground": "#FDE091"
			}
		},
		{
			"scope": "markup.italic",
			"settings": {
				"fontStyle": "italic"
			}
		},
		{
			"scope": "markup.inserted",
			"settings": {
				"foreground": "#cecea8"
			}
		},
		{
			"scope": "markup.deleted",
			"settings": {
				"foreground": "#FDE091"
			}
		},
		{
			"scope": "markup.changed",
			"settings": {
				"foreground": "#FDE091"
			}
		},
		{
			"scope": "beginning.punctuation.definition.quote.markdown",
			"settings": {
				"foreground": "#608b4e"
			}
		},
		{
			"scope": "beginning.punctuation.definition.list.markdown",
			"settings": {
				"foreground": "#6796e6"
			}
		},
		{
			"scope": "markup.inline.raw",
			"settings": {
				"foreground": "#FDE091"
			}
		},
		{
			"scope": "meta.selector",
			"settings": {
				"foreground": "#FDE091"
			}
		},
		{
			"name": "brackets of XML/HTML tags",
			"scope": "punctuation.definition.tag",
			"settings": {
				"foreground": "#808080"
			}
		},
		{
			"scope": "meta.preprocessor",
			"settings": {
				"foreground": "#FDE091"
			}
		},
		{
			"scope": "meta.preprocessor.string",
			"settings": {
				"foreground": "#FDE091"
			}
		},
		{
			"scope": "meta.preprocessor.numeric",
			"settings": {
				"foreground": "#eeb150"
			}
		},
		{
			"scope": "meta.structure.dictionary.key.python",
			"settings": {
				"foreground": "#01D6A7"
			}
		},
		{
			"scope": "meta.diff.header",
			"settings": {
				"foreground": "#FDE091"
			}
		},
		{
			"scope": "storage",
			"settings": {
				"foreground": "#FDE091"
			}
		},
		{
			"scope": "storage.modifier",
			"settings": {
				"foreground": "#FDE091",
				"fontStyle": "italic"
			}
		},
		{
			"scope": "keyword.operator.expression.delete",
			"settings": {
				"foreground": "#FDE091",
				"fontStyle": "italic"
			}
		},
		{
			"scope": "string",
			"settings": {
				"foreground": "#dddddd"
			}
		},
		{
			"scope": "string.tag",
			"settings": {
				"foreground": "#FDE091"
			}
		},
		{
			"scope": "string.value",
			"settings": {
				"foreground": "#FDE091"
			}
		},
		{
			"scope": "string.regexp",
			"settings": {
				"foreground": "#d16969"
			}
		},
		{
			"name": "String interpolation",
			"scope": [
				"punctuation.definition.template-expression.begin",
				"punctuation.definition.template-expression.end",
				"punctuation.section.embedded"
			],
			"settings": {
				"foreground": "#01D6A7"
			}
		},
		{
			"name": "Reset JavaScript string interpolation expression",
			"scope": ["meta.template.expression"],
			"settings": {
				"foreground": "#c9c9c9"
			}
		},
		{
			"scope": [
				"support.type.vendored.property-name",
				"support.type.property-name",
				"variable.css",
				"variable.scss",
				"variable.other.less",
				"source.coffee.embedded"
			],
			"settings": {
				"foreground": "#dadada"
			}
		},
		{
			"scope": "keyword",
			"settings": {
				"foreground": "#FDE091"
			}
		},
		{
			"scope": "keyword.operator",
			"settings": {
				"foreground": "#eeb150"
			}
		},
		{
			"scope": [
				"keyword.operator.new",
				"keyword.operator.expression",
				"keyword.operator.cast",
				"keyword.operator.sizeof",
				"keyword.operator.instanceof",
				"keyword.operator.logical.python",
				"storage.type",
				"variable.language.this"
			],
			"settings": {
				"foreground": "#eeb150"
			}
		},
		{
			"scope": ["storage.type.function.arrow.js"],
			"settings": {
				"foreground": "#eeb150",
				"fontStyle": "italic"
			}
		},
		{
			"scope": "keyword.other.unit",
			"settings": {
				"foreground": "#EEB772"
			}
		},
		{
			"scope": [
				"punctuation.section.embedded.begin.php",
				"punctuation.section.embedded.end.php"
			],
			"settings": {
				"foreground": "#FDE091"
			}
		},
		{
			"scope": "support.function.git-rebase",
			"settings": {
				"foreground": "#01D6A7"
			}
		},
		{
			"scope": "constant.sha.git-rebase",
			"settings": {
				"foreground": "#cecea8"
			}
		},
		{
			"name": "coloring of the Java import and package identifiers",
			"scope": [
				"storage.modifier.import.java",
				"variable.language.wildcard.java",
				"storage.modifier.package.java"
			],
			"settings": {
				"foreground": "#e2e3e4"
			}
		},
		{
			"name": "this.self",
			"scope": "variable.language",
			"settings": {
				"foreground": "#FDE091"
			}
		},
		{
			"name": "Ponctuations",
			"scope": [
				"meta.var.expr",
				"punctuation.definition.block",
				"meta.function.js",
				"keyword.operator.assignment.compound",
				"punctuation.acessor.js",
				"punctuation.separator.comma.js"
			],
			"settings": {
				"foreground": "#EEB150"
			}
		},
		{
			"name": "Ponctuations",
			"scope": [
				"keyword.operator.assignment"
			],
			"settings": {
				"foreground": "#EEB150"
			}
		},
		{
			"name": "Ponctuations Yellow",
			"scope": [
				"keyword.operator.assignment.compound",
				"keyword.operator.comparison",
				"punctuation.section.property-list.begin.bracket.curly.css"
			],
			"settings": {
				"foreground": "#EEB772"
			}
		},
		{
			"name": "Ponctuations",
			"scope": [
				"storage.type.function.arrow.js"
			],
			"settings": {
				"foreground": "#BD2222"
			}
		},
		{
			"name": "Ponctuations",
			"scope": [
				"string.quoted.double.js"
			],
			"settings": {
				"foreground": "#d1d1d1"
			}
		},
		{
			"name": "HTML String",
			"scope": [
				"string.quoted.double.html",
				"meta.attribute.class.html"
			],
			"settings": {
				"foreground": "#9ec3f3"
			}
		},
		{
			"name": "HTML TAG",
			"scope": "entity.name.tag",
			"settings": {
				"foreground": "#EEB150"
			}
		},
		{
			"name": "HTML ATRIBUTO",
			"scope": "entity.other.attribute-name",
			"settings": {
				"foreground": "#c596eb",
				"fontStyle": "italic"
			}
		}
	]
}